README.md
setup.py
beep/__init__.py
fuck/ProfanityHandler.py
fuck/__init__.py
fuck/__main__.py
fuck/util/__init__.py
fuck/util/augmentation.py
fuck/util/shape.py
fuck/util/string.py
raconteur.egg-info/PKG-INFO
raconteur.egg-info/SOURCES.txt
raconteur.egg-info/dependency_links.txt
raconteur.egg-info/requires.txt
raconteur.egg-info/top_level.txt
rr/Bark.py
rr/Coqui.py
rr/Crt.py
rr/Raconteur.py
rr/RaconteurFactory.py
rr/RuTTS.py
rr/SaluteSpeech.py
rr/Silero.py
rr/SpeechIndex.py
rr/Splitter.py
rr/__init__.py
rr/__main__.py
rr/util/__init__.py
rr/util/file.py
rr/util/string.py
rr/util/validation.py
test/test_splitter.py