Metadata-Version: 2.1
Name: raconteur
Version: 0.5
Summary: An auxiliary app for simplifying speech synthesis on arbitrary texts
Home-page: https://github.com/zeionara/raconteur
Author: Zeio Nara
Author-email: zeionara@gmail.com
License: Apache 2.0
Keywords: speech,synthesis
Classifier: Programming Language :: Python :: 3.11
